[
  {
    "ContainingType": "InstantPay.API.Controller.DashboardController",
    "Method": "GetDashboard",
    "RelativePath": "api/Dashboard",
    "HttpMethod": "GET",
    "IsController": true,
    "Order": 0,
    "Parameters": [],
    "ReturnTypes": []
  },
  {
    "ContainingType": "InstantPay.API.Controller.LoginController",
    "Method": "Login",
    "RelativePath": "api/Login",
    "HttpMethod": "POST",
    "IsController": true,
    "Order": 0,
    "Parameters": [
      {
        "Name": "request",
        "Type": "InstantPay.Application.DTOs.EncryptedRequest",
        "IsRequired": true
      }
    ],
    "ReturnTypes": []
  },
  {
    "ContainingType": "InstantPay.API.Controller.LoginController",
    "Method": "ResendOTP",
    "RelativePath": "api/Login/resendotp",
    "HttpMethod": "POST",
    "IsController": true,
    "Order": 0,
    "Parameters": [
      {
        "Name": "request",
        "Type": "InstantPay.Application.DTOs.EncryptedRequest",
        "IsRequired": true
      }
    ],
    "ReturnTypes": []
  },
  {
    "ContainingType": "InstantPay.API.Controller.LoginController",
    "Method": "VerifyOTP",
    "RelativePath": "api/Login/verifyotp",
    "HttpMethod": "POST",
    "IsController": true,
    "Order": 0,
    "Parameters": [
      {
        "Name": "request",
        "Type": "InstantPay.Application.DTOs.EncryptedRequest",
        "IsRequired": true
      }
    ],
    "ReturnTypes": []
  },
  {
    "ContainingType": "InstantPay.API.Controller.MasterController",
    "Method": "GetSuperAdminDashboardData",
    "RelativePath": "api/Master/GetSuperAdminDashboardData",
    "HttpMethod": "POST",
    "IsController": true,
    "Order": 0,
    "Parameters": [
      {
        "Name": "request",
        "Type": "InstantPay.Application.DTOs.EncryptedRequest",
        "IsRequired": true
      }
    ],
    "ReturnTypes": []
  },
  {
    "ContainingType": "InstantPay.API.Controller.OperatorController",
    "Method": "GetOperators",
    "RelativePath": "api/Operator/get-operators",
    "HttpMethod": "POST",
    "IsController": true,
    "Order": 0,
    "Parameters": [
      {
        "Name": "request",
        "Type": "InstantPay.SharedKernel.Entity.EncryptedRequestDto",
        "IsRequired": true
      }
    ],
    "ReturnTypes": []
  },
  {
    "ContainingType": "InstantPay.API.Controller.RechargeController",
    "Method": "SubmitRecharge",
    "RelativePath": "api/Recharge/submit",
    "HttpMethod": "POST",
    "IsController": true,
    "Order": 0,
    "Parameters": [
      {
        "Name": "request",
        "Type": "InstantPay.Application.DTOs.EncryptedRequest",
        "IsRequired": true
      }
    ],
    "ReturnTypes": []
  },
  {
    "ContainingType": "InstantPay.API.Controller.ReportController",
    "Method": "TxnReport",
    "RelativePath": "api/Report/Txn-Report",
    "HttpMethod": "POST",
    "IsController": true,
    "Order": 0,
    "Parameters": [
      {
        "Name": "request",
        "Type": "InstantPay.Application.DTOs.EncryptedRequest",
        "IsRequired": true
      }
    ],
    "ReturnTypes": []
  }
]